<?xml version="1.0" encoding="utf-8"?><index><!-- saved from url=(0016)http://localhost -->
<stem n="operations"><phr n="operations"><ent r="82" t="17" w="11" /><ent r="82" t="17" w="11" /><ent r="8" t="17" w="291" /><ent r="8" t="17" w="291" /><ent r="6" t="22" w="105" /><ent r="6" t="22" w="105" /><ent r="8" t="43" w="139" /><ent r="8" t="43" w="139" /><ent r="6" t="46" w="69" /><ent r="6" t="46" w="69" /><ent r="6" t="51" w="163" /><ent r="6" t="59" w="122" /><ent r="1000" t="76" w="5" /><ent r="1000" t="76" w="5" /><ent r="102" t="76" w="11" /><ent r="102" t="76" w="11" /><ent r="8" t="94" w="59" /><ent r="8" t="94" w="59" /><ent r="6" t="123" w="144" /><ent r="6" t="123" w="144" /><ent r="6" t="129" w="277" /><ent r="6" t="129" w="277" /><ent r="5" t="132" w="64" /><ent r="5" t="132" w="109" /><ent r="6" t="134" w="41" /><ent r="6" t="134" w="41" /><ent r="6" t="134" w="244" /><ent r="6" t="134" w="244" /><ent r="3" t="139" w="29" /><ent r="3" t="139" w="213" /><ent r="3" t="139" w="213" /><ent r="6" t="153" w="34" /><ent r="7" t="155" w="52" /><ent r="7" t="155" w="52" /><ent r="6" t="156" w="50" /><ent r="6" t="157" w="46" /><ent r="6" t="158" w="46" /><ent r="6" t="158" w="46" /><ent r="6" t="160" w="94" /><ent r="6" t="161" w="50" /><ent r="6" t="162" w="51" /><ent r="8" t="164" w="128" /><ent r="8" t="164" w="128" /><ent r="8" t="164" w="971" /><ent r="8" t="164" w="971" /><ent r="6" t="168" w="85" /><ent r="6" t="168" w="85" /><ent r="6" t="168" w="92" /><ent r="6" t="180" w="184" /><ent r="6" t="182" w="166" /><ent r="3" t="183" w="35" /><ent r="6" t="183" w="198" /><ent r="6" t="183" w="198" /><ent r="6" t="183" w="477" /><ent r="6" t="185" w="54" /><ent r="6" t="185" w="94" /><ent r="6" t="185" w="124" /><ent r="6" t="185" w="124" /><ent r="5" t="191" w="75" /><ent r="5" t="191" w="584" /><ent r="5" t="191" w="584" /></phr><phr n="Operations"><ent r="6" t="91" w="72" /><ent r="6" t="91" w="72" /><ent r="6" t="91" w="85" /><ent r="6" t="91" w="85" /></phr></stem><stem n="ecki"><phr n="Checking"><ent r="66" t="17" w="13" /><ent r="66" t="17" w="13" /><ent r="3" t="17" w="46" /><ent r="3" t="17" w="46" /><ent r="5" t="17" w="539" /><ent r="5" t="17" w="539" /><ent r="6" t="19" w="22" /><ent r="6" t="19" w="22" /><ent r="82" t="44" w="9" /><ent r="82" t="44" w="9" /><ent r="66" t="44" w="13" /><ent r="66" t="44" w="13" /><ent r="66" t="44" w="53" /><ent r="66" t="44" w="53" /><ent r="3" t="44" w="62" /><ent r="3" t="44" w="62" /><ent r="5" t="44" w="633" /><ent r="5" t="44" w="633" /><ent r="3" t="44" w="785" /><ent r="3" t="44" w="785" /><ent r="66" t="145" w="29" /><ent r="66" t="145" w="29" /><ent r="3" t="145" w="143" /><ent r="3" t="145" w="143" /></phr><phr n="checking"><ent r="6" t="18" w="29" /><ent r="6" t="18" w="29" /><ent r="8" t="45" w="125" /><ent r="8" t="45" w="125" /><ent r="1000" t="76" w="2" /><ent r="1000" t="76" w="2" /><ent r="102" t="76" w="8" /><ent r="102" t="76" w="8" /><ent r="1000" t="136" w="3" /><ent r="1000" t="136" w="3" /></phr></stem><stem n="hecki"><phr n="Checking"><ent r="66" t="17" w="13" /><ent r="66" t="17" w="13" /><ent r="3" t="17" w="46" /><ent r="3" t="17" w="46" /><ent r="5" t="17" w="539" /><ent r="5" t="17" w="539" /><ent r="6" t="19" w="22" /><ent r="6" t="19" w="22" /><ent r="82" t="44" w="9" /><ent r="82" t="44" w="9" /><ent r="66" t="44" w="13" /><ent r="66" t="44" w="13" /><ent r="66" t="44" w="53" /><ent r="66" t="44" w="53" /><ent r="3" t="44" w="62" /><ent r="3" t="44" w="62" /><ent r="5" t="44" w="633" /><ent r="5" t="44" w="633" /><ent r="3" t="44" w="785" /><ent r="3" t="44" w="785" /><ent r="66" t="145" w="29" /><ent r="66" t="145" w="29" /><ent r="3" t="145" w="143" /><ent r="3" t="145" w="143" /></phr><phr n="checking"><ent r="6" t="18" w="29" /><ent r="6" t="18" w="29" /><ent r="8" t="45" w="125" /><ent r="8" t="45" w="125" /><ent r="1000" t="76" w="2" /><ent r="1000" t="76" w="2" /><ent r="102" t="76" w="8" /><ent r="102" t="76" w="8" /><ent r="1000" t="136" w="3" /><ent r="1000" t="136" w="3" /></phr></stem><stem n="eckin"><phr n="Checking"><ent r="66" t="17" w="13" /><ent r="66" t="17" w="13" /><ent r="3" t="17" w="46" /><ent r="3" t="17" w="46" /><ent r="5" t="17" w="539" /><ent r="5" t="17" w="539" /><ent r="6" t="19" w="22" /><ent r="6" t="19" w="22" /><ent r="82" t="44" w="9" /><ent r="82" t="44" w="9" /><ent r="66" t="44" w="13" /><ent r="66" t="44" w="13" /><ent r="66" t="44" w="53" /><ent r="66" t="44" w="53" /><ent r="3" t="44" w="62" /><ent r="3" t="44" w="62" /><ent r="5" t="44" w="633" /><ent r="5" t="44" w="633" /><ent r="3" t="44" w="785" /><ent r="3" t="44" w="785" /><ent r="66" t="145" w="29" /><ent r="66" t="145" w="29" /><ent r="3" t="145" w="143" /><ent r="3" t="145" w="143" /></phr><phr n="checking"><ent r="6" t="18" w="29" /><ent r="6" t="18" w="29" /><ent r="8" t="45" w="125" /><ent r="8" t="45" w="125" /><ent r="1000" t="76" w="2" /><ent r="1000" t="76" w="2" /><ent r="102" t="76" w="8" /><ent r="102" t="76" w="8" /><ent r="1000" t="136" w="3" /><ent r="1000" t="136" w="3" /></phr></stem><stem n="checki"><phr n="Checking"><ent r="66" t="17" w="13" /><ent r="66" t="17" w="13" /><ent r="3" t="17" w="46" /><ent r="3" t="17" w="46" /><ent r="5" t="17" w="539" /><ent r="5" t="17" w="539" /><ent r="6" t="19" w="22" /><ent r="6" t="19" w="22" /><ent r="82" t="44" w="9" /><ent r="82" t="44" w="9" /><ent r="66" t="44" w="13" /><ent r="66" t="44" w="13" /><ent r="66" t="44" w="53" /><ent r="66" t="44" w="53" /><ent r="3" t="44" w="62" /><ent r="3" t="44" w="62" /><ent r="5" t="44" w="633" /><ent r="5" t="44" w="633" /><ent r="3" t="44" w="785" /><ent r="3" t="44" w="785" /><ent r="66" t="145" w="29" /><ent r="66" t="145" w="29" /><ent r="3" t="145" w="143" /><ent r="3" t="145" w="143" /></phr><phr n="checking"><ent r="6" t="18" w="29" /><ent r="6" t="18" w="29" /><ent r="8" t="45" w="125" /><ent r="8" t="45" w="125" /><ent r="1000" t="76" w="2" /><ent r="1000" t="76" w="2" /><ent r="102" t="76" w="8" /><ent r="102" t="76" w="8" /><ent r="1000" t="136" w="3" /><ent r="1000" t="136" w="3" /></phr></stem><stem n="heckin"><phr n="Checking"><ent r="66" t="17" w="13" /><ent r="66" t="17" w="13" /><ent r="3" t="17" w="46" /><ent r="3" t="17" w="46" /><ent r="5" t="17" w="539" /><ent r="5" t="17" w="539" /><ent r="6" t="19" w="22" /><ent r="6" t="19" w="22" /><ent r="82" t="44" w="9" /><ent r="82" t="44" w="9" /><ent r="66" t="44" w="13" /><ent r="66" t="44" w="13" /><ent r="66" t="44" w="53" /><ent r="66" t="44" w="53" /><ent r="3" t="44" w="62" /><ent r="3" t="44" w="62" /><ent r="5" t="44" w="633" /><ent r="5" t="44" w="633" /><ent r="3" t="44" w="785" /><ent r="3" t="44" w="785" /><ent r="66" t="145" w="29" /><ent r="66" t="145" w="29" /><ent r="3" t="145" w="143" /><ent r="3" t="145" w="143" /></phr><phr n="checking"><ent r="6" t="18" w="29" /><ent r="6" t="18" w="29" /><ent r="8" t="45" w="125" /><ent r="8" t="45" w="125" /><ent r="1000" t="76" w="2" /><ent r="1000" t="76" w="2" /><ent r="102" t="76" w="8" /><ent r="102" t="76" w="8" /><ent r="1000" t="136" w="3" /><ent r="1000" t="136" w="3" /></phr></stem><stem n="ecking"><phr n="Checking"><ent r="66" t="17" w="13" /><ent r="66" t="17" w="13" /><ent r="3" t="17" w="46" /><ent r="3" t="17" w="46" /><ent r="5" t="17" w="539" /><ent r="5" t="17" w="539" /><ent r="6" t="19" w="22" /><ent r="6" t="19" w="22" /><ent r="82" t="44" w="9" /><ent r="82" t="44" w="9" /><ent r="66" t="44" w="13" /><ent r="66" t="44" w="13" /><ent r="66" t="44" w="53" /><ent r="66" t="44" w="53" /><ent r="3" t="44" w="62" /><ent r="3" t="44" w="62" /><ent r="5" t="44" w="633" /><ent r="5" t="44" w="633" /><ent r="3" t="44" w="785" /><ent r="3" t="44" w="785" /><ent r="66" t="145" w="29" /><ent r="66" t="145" w="29" /><ent r="3" t="145" w="143" /><ent r="3" t="145" w="143" /></phr><phr n="checking"><ent r="6" t="18" w="29" /><ent r="6" t="18" w="29" /><ent r="8" t="45" w="125" /><ent r="8" t="45" w="125" /><ent r="1000" t="76" w="2" /><ent r="1000" t="76" w="2" /><ent r="102" t="76" w="8" /><ent r="102" t="76" w="8" /><ent r="1000" t="136" w="3" /><ent r="1000" t="136" w="3" /></phr></stem><stem n="checkin"><phr n="Checking"><ent r="66" t="17" w="13" /><ent r="66" t="17" w="13" /><ent r="3" t="17" w="46" /><ent r="3" t="17" w="46" /><ent r="5" t="17" w="539" /><ent r="5" t="17" w="539" /><ent r="6" t="19" w="22" /><ent r="6" t="19" w="22" /><ent r="82" t="44" w="9" /><ent r="82" t="44" w="9" /><ent r="66" t="44" w="13" /><ent r="66" t="44" w="13" /><ent r="66" t="44" w="53" /><ent r="66" t="44" w="53" /><ent r="3" t="44" w="62" /><ent r="3" t="44" w="62" /><ent r="5" t="44" w="633" /><ent r="5" t="44" w="633" /><ent r="3" t="44" w="785" /><ent r="3" t="44" w="785" /><ent r="66" t="145" w="29" /><ent r="66" t="145" w="29" /><ent r="3" t="145" w="143" /><ent r="3" t="145" w="143" /></phr><phr n="checking"><ent r="6" t="18" w="29" /><ent r="6" t="18" w="29" /><ent r="8" t="45" w="125" /><ent r="8" t="45" w="125" /><ent r="1000" t="76" w="2" /><ent r="1000" t="76" w="2" /><ent r="102" t="76" w="8" /><ent r="102" t="76" w="8" /><ent r="1000" t="136" w="3" /><ent r="1000" t="136" w="3" /></phr></stem><stem n="hecking"><phr n="Checking"><ent r="66" t="17" w="13" /><ent r="66" t="17" w="13" /><ent r="3" t="17" w="46" /><ent r="3" t="17" w="46" /><ent r="5" t="17" w="539" /><ent r="5" t="17" w="539" /><ent r="6" t="19" w="22" /><ent r="6" t="19" w="22" /><ent r="82" t="44" w="9" /><ent r="82" t="44" w="9" /><ent r="66" t="44" w="13" /><ent r="66" t="44" w="13" /><ent r="66" t="44" w="53" /><ent r="66" t="44" w="53" /><ent r="3" t="44" w="62" /><ent r="3" t="44" w="62" /><ent r="5" t="44" w="633" /><ent r="5" t="44" w="633" /><ent r="3" t="44" w="785" /><ent r="3" t="44" w="785" /><ent r="66" t="145" w="29" /><ent r="66" t="145" w="29" /><ent r="3" t="145" w="143" /><ent r="3" t="145" w="143" /></phr><phr n="checking"><ent r="6" t="18" w="29" /><ent r="6" t="18" w="29" /><ent r="8" t="45" w="125" /><ent r="8" t="45" w="125" /><ent r="1000" t="76" w="2" /><ent r="1000" t="76" w="2" /><ent r="102" t="76" w="8" /><ent r="102" t="76" w="8" /><ent r="1000" t="136" w="3" /><ent r="1000" t="136" w="3" /></phr></stem><stem n="checking"><phr n="Checking"><ent r="66" t="17" w="13" /><ent r="66" t="17" w="13" /><ent r="3" t="17" w="46" /><ent r="3" t="17" w="46" /><ent r="5" t="17" w="539" /><ent r="5" t="17" w="539" /><ent r="6" t="19" w="22" /><ent r="6" t="19" w="22" /><ent r="82" t="44" w="9" /><ent r="82" t="44" w="9" /><ent r="66" t="44" w="13" /><ent r="66" t="44" w="13" /><ent r="66" t="44" w="53" /><ent r="66" t="44" w="53" /><ent r="3" t="44" w="62" /><ent r="3" t="44" w="62" /><ent r="5" t="44" w="633" /><ent r="5" t="44" w="633" /><ent r="3" t="44" w="785" /><ent r="3" t="44" w="785" /><ent r="66" t="145" w="29" /><ent r="66" t="145" w="29" /><ent r="3" t="145" w="143" /><ent r="3" t="145" w="143" /></phr><phr n="checking"><ent r="6" t="18" w="29" /><ent r="6" t="18" w="29" /><ent r="8" t="45" w="125" /><ent r="8" t="45" w="125" /><ent r="1000" t="76" w="2" /><ent r="1000" t="76" w="2" /><ent r="102" t="76" w="8" /><ent r="102" t="76" w="8" /><ent r="1000" t="136" w="3" /><ent r="1000" t="136" w="3" /></phr></stem><stem n="lower"><phr n="lower"><ent r="8" t="17" w="79" /><ent r="8" t="17" w="79" /><ent r="4" t="33" w="636" /><ent r="4" t="33" w="636" /><ent r="6" t="184" w="67" /><ent r="6" t="184" w="67" /></phr><phr n="lowers"><ent r="3" t="137" w="81" /><ent r="3" t="137" w="81" /></phr></stem><stem n="ower"><phr n="lower"><ent r="8" t="17" w="79" /><ent r="8" t="17" w="79" /><ent r="4" t="33" w="636" /><ent r="4" t="33" w="636" /><ent r="6" t="184" w="67" /><ent r="6" t="184" w="67" /></phr><phr n="power"><ent r="6" t="123" w="58" /><ent r="6" t="123" w="58" /><ent r="3" t="124" w="32" /><ent r="3" t="124" w="32" /><ent r="3" t="124" w="461" /><ent r="5" t="125" w="154" /><ent r="5" t="125" w="154" /><ent r="5" t="127" w="103" /><ent r="5" t="127" w="151" /><ent r="6" t="134" w="89" /><ent r="6" t="134" w="89" /><ent r="5" t="186" w="49" /><ent r="5" t="186" w="49" /></phr><phr n="lowers"><ent r="3" t="137" w="81" /><ent r="3" t="137" w="81" /></phr><phr n="powerful"><ent r="3" t="188" w="340" /><ent r="3" t="188" w="340" /></phr></stem><stem n="acknowledg"><phr n="acknowledge"><ent r="8" t="17" w="122" /><ent r="8" t="17" w="122" /><ent r="6" t="19" w="39" /><ent r="6" t="19" w="39" /><ent r="6" t="61" w="39" /><ent r="6" t="61" w="39" /><ent r="6" t="61" w="130" /><ent r="6" t="61" w="133" /><ent r="8" t="172" w="35" /><ent r="8" t="172" w="35" /><ent r="6" t="174" w="47" /><ent r="6" t="174" w="47" /><ent r="5" t="191" w="456" /><ent r="5" t="191" w="456" /></phr><phr n="Acknowledging"><ent r="6" t="19" w="29" /><ent r="6" t="19" w="29" /><ent r="6" t="21" w="84" /><ent r="6" t="21" w="84" /><ent r="7" t="21" w="119" /><ent r="7" t="21" w="119" /></phr><phr n="Acknowledge"><ent r="6" t="19" w="151" /><ent r="6" t="19" w="151" /><ent r="7" t="19" w="211" /><ent r="7" t="19" w="211" /><ent r="6" t="20" w="128" /><ent r="6" t="20" w="128" /></phr><phr n="acknowledgement"><ent r="6" t="19" w="164" /><ent r="6" t="19" w="164" /><ent r="6" t="20" w="141" /><ent r="6" t="20" w="141" /><ent r="6" t="22" w="40" /><ent r="6" t="60" w="80" /><ent r="6" t="60" w="80" /><ent r="6" t="61" w="93" /></phr><phr n="acknowledged"><ent r="6" t="19" w="241" /><ent r="6" t="19" w="241" /><ent r="6" t="19" w="255" /><ent r="6" t="19" w="255" /><ent r="6" t="21" w="337" /><ent r="8" t="25" w="94" /><ent r="8" t="25" w="94" /><ent r="6" t="61" w="61" /><ent r="6" t="61" w="100" /><ent r="6" t="61" w="100" /><ent r="3" t="179" w="92" /><ent r="6" t="183" w="238" /><ent r="6" t="183" w="238" /><ent r="3" t="185" w="320" /><ent r="3" t="185" w="320" /></phr><phr n="acknowledges"><ent r="6" t="61" w="140" /><ent r="6" t="61" w="140" /><ent r="9" t="85" w="137" /><ent r="9" t="85" w="137" /></phr></stem><stem n="ckn"><phr n="acknowledge"><ent r="8" t="17" w="122" /><ent r="8" t="17" w="122" /><ent r="6" t="19" w="39" /><ent r="6" t="19" w="39" /><ent r="6" t="61" w="39" /><ent r="6" t="61" w="39" /><ent r="6" t="61" w="130" /><ent r="6" t="61" w="133" /><ent r="8" t="172" w="35" /><ent r="8" t="172" w="35" /><ent r="6" t="174" w="47" /><ent r="6" t="174" w="47" /><ent r="5" t="191" w="456" /><ent r="5" t="191" w="456" /></phr><phr n="Acknowledging"><ent r="6" t="19" w="29" /><ent r="6" t="19" w="29" /><ent r="6" t="21" w="84" /><ent r="6" t="21" w="84" /><ent r="7" t="21" w="119" /><ent r="7" t="21" w="119" /></phr><phr n="Acknowledge"><ent r="6" t="19" w="151" /><ent r="6" t="19" w="151" /><ent r="7" t="19" w="211" /><ent r="7" t="19" w="211" /><ent r="6" t="20" w="128" /><ent r="6" t="20" w="128" /></phr><phr n="acknowledgement"><ent r="6" t="19" w="164" /><ent r="6" t="19" w="164" /><ent r="6" t="20" w="141" /><ent r="6" t="20" w="141" /><ent r="6" t="22" w="40" /><ent r="6" t="60" w="80" /><ent r="6" t="60" w="80" /><ent r="6" t="61" w="93" /></phr><phr n="acknowledged"><ent r="6" t="19" w="241" /><ent r="6" t="19" w="241" /><ent r="6" t="19" w="255" /><ent r="6" t="19" w="255" /><ent r="6" t="21" w="337" /><ent r="8" t="25" w="94" /><ent r="8" t="25" w="94" /><ent r="6" t="61" w="61" /><ent r="6" t="61" w="100" /><ent r="6" t="61" w="100" /><ent r="3" t="179" w="92" /><ent r="6" t="183" w="238" /><ent r="6" t="183" w="238" /><ent r="3" t="185" w="320" /><ent r="3" t="185" w="320" /></phr><phr n="acknowledges"><ent r="6" t="61" w="140" /><ent r="6" t="61" w="140" /><ent r="9" t="85" w="137" /><ent r="9" t="85" w="137" /></phr></stem><stem n="owl"><phr n="acknowledge"><ent r="8" t="17" w="122" /><ent r="8" t="17" w="122" /><ent r="6" t="19" w="39" /><ent r="6" t="19" w="39" /><ent r="6" t="61" w="39" /><ent r="6" t="61" w="39" /><ent r="6" t="61" w="130" /><ent r="6" t="61" w="133" /><ent r="8" t="172" w="35" /><ent r="8" t="172" w="35" /><ent r="6" t="174" w="47" /><ent r="6" t="174" w="47" /><ent r="5" t="191" w="456" /><ent r="5" t="191" w="456" /></phr><phr n="Acknowledging"><ent r="6" t="19" w="29" /><ent r="6" t="19" w="29" /><ent r="6" t="21" w="84" /><ent r="6" t="21" w="84" /><ent r="7" t="21" w="119" /><ent r="7" t="21" w="119" /></phr><phr n="Acknowledge"><ent r="6" t="19" w="151" /><ent r="6" t="19" w="151" /><ent r="7" t="19" w="211" /><ent r="7" t="19" w="211" /><ent r="6" t="20" w="128" /><ent r="6" t="20" w="128" /></phr><phr n="acknowledgement"><ent r="6" t="19" w="164" /><ent r="6" t="19" w="164" /><ent r="6" t="20" w="141" /><ent r="6" t="20" w="141" /><ent r="6" t="22" w="40" /><ent r="6" t="60" w="80" /><ent r="6" t="60" w="80" /><ent r="6" t="61" w="93" /></phr><phr n="acknowledged"><ent r="6" t="19" w="241" /><ent r="6" t="19" w="241" /><ent r="6" t="19" w="255" /><ent r="6" t="19" w="255" /><ent r="6" t="21" w="337" /><ent r="8" t="25" w="94" /><ent r="8" t="25" w="94" /><ent r="6" t="61" w="61" /><ent r="6" t="61" w="100" /><ent r="6" t="61" w="100" /><ent r="3" t="179" w="92" /><ent r="6" t="183" w="238" /><ent r="6" t="183" w="238" /><ent r="3" t="185" w="320" /><ent r="3" t="185" w="320" /></phr><phr n="acknowledges"><ent r="6" t="61" w="140" /><ent r="6" t="61" w="140" /><ent r="9" t="85" w="137" /><ent r="9" t="85" w="137" /></phr><phr n="Knowledge"><ent r="3" t="173" w="87" /><ent r="3" t="173" w="87" /></phr><phr n="knowledge"><ent r="3" t="173" w="99" /><ent r="3" t="173" w="99" /></phr></stem><stem n="edg"><phr n="acknowledge"><ent r="8" t="17" w="122" /><ent r="8" t="17" w="122" /><ent r="6" t="19" w="39" /><ent r="6" t="19" w="39" /><ent r="6" t="61" w="39" /><ent r="6" t="61" w="39" /><ent r="6" t="61" w="130" /><ent r="6" t="61" w="133" /><ent r="8" t="172" w="35" /><ent r="8" t="172" w="35" /><ent r="6" t="174" w="47" /><ent r="6" t="174" w="47" /><ent r="5" t="191" w="456" /><ent r="5" t="191" w="456" /></phr><phr n="Acknowledging"><ent r="6" t="19" w="29" /><ent r="6" t="19" w="29" /><ent r="6" t="21" w="84" /><ent r="6" t="21" w="84" /><ent r="7" t="21" w="119" /><ent r="7" t="21" w="119" /></phr><phr n="Acknowledge"><ent r="6" t="19" w="151" /><ent r="6" t="19" w="151" /><ent r="7" t="19" w="211" /><ent r="7" t="19" w="211" /><ent r="6" t="20" w="128" /><ent r="6" t="20" w="128" /></phr><phr n="acknowledgement"><ent r="6" t="19" w="164" /><ent r="6" t="19" w="164" /><ent r="6" t="20" w="141" /><ent r="6" t="20" w="141" /><ent r="6" t="22" w="40" /><ent r="6" t="60" w="80" /><ent r="6" t="60" w="80" /><ent r="6" t="61" w="93" /></phr><phr n="acknowledged"><ent r="6" t="19" w="241" /><ent r="6" t="19" w="241" /><ent r="6" t="19" w="255" /><ent r="6" t="19" w="255" /><ent r="6" t="21" w="337" /><ent r="8" t="25" w="94" /><ent r="8" t="25" w="94" /><ent r="6" t="61" w="61" /><ent r="6" t="61" w="100" /><ent r="6" t="61" w="100" /><ent r="3" t="179" w="92" /><ent r="6" t="183" w="238" /><ent r="6" t="183" w="238" /><ent r="3" t="185" w="320" /><ent r="3" t="185" w="320" /></phr><phr n="acknowledges"><ent r="6" t="61" w="140" /><ent r="6" t="61" w="140" /><ent r="9" t="85" w="137" /><ent r="9" t="85" w="137" /></phr><phr n="Knowledge"><ent r="3" t="173" w="87" /><ent r="3" t="173" w="87" /></phr><phr n="knowledge"><ent r="3" t="173" w="99" /><ent r="3" t="173" w="99" /></phr></stem><stem n="wle"><phr n="acknowledge"><ent r="8" t="17" w="122" /><ent r="8" t="17" w="122" /><ent r="6" t="19" w="39" /><ent r="6" t="19" w="39" /><ent r="6" t="61" w="39" /><ent r="6" t="61" w="39" /><ent r="6" t="61" w="130" /><ent r="6" t="61" w="133" /><ent r="8" t="172" w="35" /><ent r="8" t="172" w="35" /><ent r="6" t="174" w="47" /><ent r="6" t="174" w="47" /><ent r="5" t="191" w="456" /><ent r="5" t="191" w="456" /></phr><phr n="Acknowledging"><ent r="6" t="19" w="29" /><ent r="6" t="19" w="29" /><ent r="6" t="21" w="84" /><ent r="6" t="21" w="84" /><ent r="7" t="21" w="119" /><ent r="7" t="21" w="119" /></phr><phr n="Acknowledge"><ent r="6" t="19" w="151" /><ent r="6" t="19" w="151" /><ent r="7" t="19" w="211" /><ent r="7" t="19" w="211" /><ent r="6" t="20" w="128" /><ent r="6" t="20" w="128" /></phr><phr n="acknowledgement"><ent r="6" t="19" w="164" /><ent r="6" t="19" w="164" /><ent r="6" t="20" w="141" /><ent r="6" t="20" w="141" /><ent r="6" t="22" w="40" /><ent r="6" t="60" w="80" /><ent r="6" t="60" w="80" /><ent r="6" t="61" w="93" /></phr><phr n="acknowledged"><ent r="6" t="19" w="241" /><ent r="6" t="19" w="241" /><ent r="6" t="19" w="255" /><ent r="6" t="19" w="255" /><ent r="6" t="21" w="337" /><ent r="8" t="25" w="94" /><ent r="8" t="25" w="94" /><ent r="6" t="61" w="61" /><ent r="6" t="61" w="100" /><ent r="6" t="61" w="100" /><ent r="3" t="179" w="92" /><ent r="6" t="183" w="238" /><ent r="6" t="183" w="238" /><ent r="3" t="185" w="320" /><ent r="3" t="185" w="320" /></phr><phr n="acknowledges"><ent r="6" t="61" w="140" /><ent r="6" t="61" w="140" /><ent r="9" t="85" w="137" /><ent r="9" t="85" w="137" /></phr><phr n="Knowledge"><ent r="3" t="173" w="87" /><ent r="3" t="173" w="87" /></phr><phr n="knowledge"><ent r="3" t="173" w="99" /><ent r="3" t="173" w="99" /></phr></stem><stem n="dge"><phr n="acknowledge"><ent r="8" t="17" w="122" /><ent r="8" t="17" w="122" /><ent r="6" t="19" w="39" /><ent r="6" t="19" w="39" /><ent r="6" t="61" w="39" /><ent r="6" t="61" w="39" /><ent r="6" t="61" w="130" /><ent r="6" t="61" w="133" /><ent r="8" t="172" w="35" /><ent r="8" t="172" w="35" /><ent r="6" t="174" w="47" /><ent r="6" t="174" w="47" /><ent r="5" t="191" w="456" /><ent r="5" t="191" w="456" /></phr><phr n="Acknowledge"><ent r="6" t="19" w="151" /><ent r="6" t="19" w="151" /><ent r="7" t="19" w="211" /><ent r="7" t="19" w="211" /><ent r="6" t="20" w="128" /><ent r="6" t="20" w="128" /></phr><phr n="acknowledgement"><ent r="6" t="19" w="164" /><ent r="6" t="19" w="164" /><ent r="6" t="20" w="141" /><ent r="6" t="20" w="141" /><ent r="6" t="22" w="40" /><ent r="6" t="60" w="80" /><ent r="6" t="60" w="80" /><ent r="6" t="61" w="93" /></phr><phr n="acknowledged"><ent r="6" t="19" w="241" /><ent r="6" t="19" w="241" /><ent r="6" t="19" w="255" /><ent r="6" t="19" w="255" /><ent r="6" t="21" w="337" /><ent r="8" t="25" w="94" /><ent r="8" t="25" w="94" /><ent r="6" t="61" w="61" /><ent r="6" t="61" w="100" /><ent r="6" t="61" w="100" /><ent r="3" t="179" w="92" /><ent r="6" t="183" w="238" /><ent r="6" t="183" w="238" /><ent r="3" t="185" w="320" /><ent r="3" t="185" w="320" /></phr><phr n="acknowledges"><ent r="6" t="61" w="140" /><ent r="6" t="61" w="140" /><ent r="9" t="85" w="137" /><ent r="9" t="85" w="137" /></phr><phr n="fridge"><ent r="8" t="104" w="88" /><ent r="8" t="104" w="88" /><ent r="8" t="104" w="138" /><ent r="8" t="104" w="138" /></phr><phr n="Knowledge"><ent r="3" t="173" w="87" /><ent r="3" t="173" w="87" /></phr><phr n="knowledge"><ent r="3" t="173" w="99" /><ent r="3" t="173" w="99" /></phr></stem><stem n="ackn"><phr n="acknowledge"><ent r="8" t="17" w="122" /><ent r="8" t="17" w="122" /><ent r="6" t="19" w="39" /><ent r="6" t="19" w="39" /><ent r="6" t="61" w="39" /><ent r="6" t="61" w="39" /><ent r="6" t="61" w="130" /><ent r="6" t="61" w="133" /><ent r="8" t="172" w="35" /><ent r="8" t="172" w="35" /><ent r="6" t="174" w="47" /><ent r="6" t="174" w="47" /><ent r="5" t="191" w="456" /><ent r="5" t="191" w="456" /></phr><phr n="Acknowledging"><ent r="6" t="19" w="29" /><ent r="6" t="19" w="29" /><ent r="6" t="21" w="84" /><ent r="6" t="21" w="84" /><ent r="7" t="21" w="119" /><ent r="7" t="21" w="119" /></phr><phr n="Acknowledge"><ent r="6" t="19" w="151" /><ent r="6" t="19" w="151" /><ent r="7" t="19" w="211" /><ent r="7" t="19" w="211" /><ent r="6" t="20" w="128" /><ent r="6" t="20" w="128" /></phr><phr n="acknowledgement"><ent r="6" t="19" w="164" /><ent r="6" t="19" w="164" /><ent r="6" t="20" w="141" /><ent r="6" t="20" w="141" /><ent r="6" t="22" w="40" /><ent r="6" t="60" w="80" /><ent r="6" t="60" w="80" /><ent r="6" t="61" w="93" /></phr><phr n="acknowledged"><ent r="6" t="19" w="241" /><ent r="6" t="19" w="241" /><ent r="6" t="19" w="255" /><ent r="6" t="19" w="255" /><ent r="6" t="21" w="337" /><ent r="8" t="25" w="94" /><ent r="8" t="25" w="94" /><ent r="6" t="61" w="61" /><ent r="6" t="61" w="100" /><ent r="6" t="61" w="100" /><ent r="3" t="179" w="92" /><ent r="6" t="183" w="238" /><ent r="6" t="183" w="238" /><ent r="3" t="185" w="320" /><ent r="3" t="185" w="320" /></phr><phr n="acknowledges"><ent r="6" t="61" w="140" /><ent r="6" t="61" w="140" /><ent r="9" t="85" w="137" /><ent r="9" t="85" w="137" /></phr></stem><stem n="owle"><phr n="acknowledge"><ent r="8" t="17" w="122" /><ent r="8" t="17" w="122" /><ent r="6" t="19" w="39" /><ent r="6" t="19" w="39" /><ent r="6" t="61" w="39" /><ent r="6" t="61" w="39" /><ent r="6" t="61" w="130" /><ent r="6" t="61" w="133" /><ent r="8" t="172" w="35" /><ent r="8" t="172" w="35" /><ent r="6" t="174" w="47" /><ent r="6" t="174" w="47" /><ent r="5" t="191" w="456" /><ent r="5" t="191" w="456" /></phr><phr n="Acknowledging"><ent r="6" t="19" w="29" /><ent r="6" t="19" w="29" /><ent r="6" t="21" w="84" /><ent r="6" t="21" w="84" /><ent r="7" t="21" w="119" /><ent r="7" t="21" w="119" /></phr><phr n="Acknowledge"><ent r="6" t="19" w="151" /><ent r="6" t="19" w="151" /><ent r="7" t="19" w="211" /><ent r="7" t="19" w="211" /><ent r="6" t="20" w="128" /><ent r="6" t="20" w="128" /></phr><phr n="acknowledgement"><ent r="6" t="19" w="164" /><ent r="6" t="19" w="164" /><ent r="6" t="20" w="141" /><ent r="6" t="20" w="141" /><ent r="6" t="22" w="40" /><ent r="6" t="60" w="80" /><ent r="6" t="60" w="80" /><ent r="6" t="61" w="93" /></phr><phr n="acknowledged"><ent r="6" t="19" w="241" /><ent r="6" t="19" w="241" /><ent r="6" t="19" w="255" /><ent r="6" t="19" w="255" /><ent r="6" t="21" w="337" /><ent r="8" t="25" w="94" /><ent r="8" t="25" w="94" /><ent r="6" t="61" w="61" /><ent r="6" t="61" w="100" /><ent r="6" t="61" w="100" /><ent r="3" t="179" w="92" /><ent r="6" t="183" w="238" /><ent r="6" t="183" w="238" /><ent r="3" t="185" w="320" /><ent r="3" t="185" w="320" /></phr><phr n="acknowledges"><ent r="6" t="61" w="140" /><ent r="6" t="61" w="140" /><ent r="9" t="85" w="137" /><ent r="9" t="85" w="137" /></phr><phr n="Knowledge"><ent r="3" t="173" w="87" /><ent r="3" t="173" w="87" /></phr><phr n="knowledge"><ent r="3" t="173" w="99" /><ent r="3" t="173" w="99" /></phr></stem><stem n="ckno"><phr n="acknowledge"><ent r="8" t="17" w="122" /><ent r="8" t="17" w="122" /><ent r="6" t="19" w="39" /><ent r="6" t="19" w="39" /><ent r="6" t="61" w="39" /><ent r="6" t="61" w="39" /><ent r="6" t="61" w="130" /><ent r="6" t="61" w="133" /><ent r="8" t="172" w="35" /><ent r="8" t="172" w="35" /><ent r="6" t="174" w="47" /><ent r="6" t="174" w="47" /><ent r="5" t="191" w="456" /><ent r="5" t="191" w="456" /></phr><phr n="Acknowledging"><ent r="6" t="19" w="29" /><ent r="6" t="19" w="29" /><ent r="6" t="21" w="84" /><ent r="6" t="21" w="84" /><ent r="7" t="21" w="119" /><ent r="7" t="21" w="119" /></phr><phr n="Acknowledge"><ent r="6" t="19" w="151" /><ent r="6" t="19" w="151" /><ent r="7" t="19" w="211" /><ent r="7" t="19" w="211" /><ent r="6" t="20" w="128" /><ent r="6" t="20" w="128" /></phr><phr n="acknowledgement"><ent r="6" t="19" w="164" /><ent r="6" t="19" w="164" /><ent r="6" t="20" w="141" /><ent r="6" t="20" w="141" /><ent r="6" t="22" w="40" /><ent r="6" t="60" w="80" /><ent r="6" t="60" w="80" /><ent r="6" t="61" w="93" /></phr><phr n="acknowledged"><ent r="6" t="19" w="241" /><ent r="6" t="19" w="241" /><ent r="6" t="19" w="255" /><ent r="6" t="19" w="255" /><ent r="6" t="21" w="337" /><ent r="8" t="25" w="94" /><ent r="8" t="25" w="94" /><ent r="6" t="61" w="61" /><ent r="6" t="61" w="100" /><ent r="6" t="61" w="100" /><ent r="3" t="179" w="92" /><ent r="6" t="183" w="238" /><ent r="6" t="183" w="238" /><ent r="3" t="185" w="320" /><ent r="3" t="185" w="320" /></phr><phr n="acknowledges"><ent r="6" t="61" w="140" /><ent r="6" t="61" w="140" /><ent r="9" t="85" w="137" /><ent r="9" t="85" w="137" /></phr></stem></index>